pyrtls-0.1.3.dist-info/METADATA
pyrtls-0.1.3.dist-info/WHEEL
pyrtls/__init__.py
pyrtls/pyrtls.cp310-win_amd64.pyd
pyrtls-0.1.3.dist-info/RECORD
