Metadata-Version: 2.3
Name: pyrtls
Version: 0.1.3
Classifier: Programming Language :: Rust
Classifier: Programming Language :: Python :: Implementation :: CPython
Classifier: Programming Language :: Python :: Implementation :: PyPy
License: MIT OR Apache-2.0
Requires-Python: >=3.7
